reach/__init__.py
reach/autoreach.py
reach/reach.py
reach-4.1.1.dist-info/LICENSE
reach-4.1.1.dist-info/METADATA
reach-4.1.1.dist-info/WHEEL
reach-4.1.1.dist-info/top_level.txt
reach-4.1.1.dist-info/zip-safe
reach-4.1.1.dist-info/RECORD
