Metadata-Version: 2.1
Name: reach
Version: 4.1.1
Summary: A light-weight package for working with pre-trained word embeddings
Home-page: https://github.com/stephantul/reach
Author: Stéphan Tulkens
Author-email: stephantul@gmail.com
License: MIT
Project-URL: Source Code, https://github.com/stephantul/reach
Project-URL: Issue Tracker, https://github.com/stephantul/reach/issues
Keywords: word vectors,natural language processing,embeddings
Classifier: Intended Audience :: Science/Research
Classifier: Programming Language :: Python :: 3
Classifier: Programming Language :: Python :: 3.7
Classifier: Programming Language :: Python :: 3.8
Classifier: Programming Language :: Python :: 3.9
Classifier: Programming Language :: Python :: 3.10
Classifier: Programming Language :: Python :: 3.11
Classifier: License :: OSI Approved :: MIT License
Classifier: Topic :: Scientific/Engineering
Classifier: Topic :: Scientific/Engineering :: Artificial Intelligence
License-File: LICENSE
Requires-Dist: numpy
Requires-Dist: tqdm
Provides-Extra: auto
Requires-Dist: pyahocorasick ; extra == 'auto'
